analytics/__init__.py
analytics/peer_rating.py
analytics/statistics.py
api/__init__.py
api/client.py
api/methods.py
api/types.py
components/__init__.py
components/enhanced_media.py
components/games.py
components/keyboards.py
components/media.py
components/passport.py
components/payments.py
components/mini_apps/__init__.py
components/mini_apps/crypto_wallet.py
features/__init__.py
features/boost.py
features/forums.py
features/pinned_messages.py
features/polls.py
features/reactions.py
features/reactions_translation.py
features/stories.py
features/threads.py
handlers/__init__.py
handlers/callback_handler.py
handlers/command_handler.py
handlers/inline_handler.py
handlers/message_handler.py
management/__init__.py
management/channels.py
management/groups.py
management/users.py
utils/__init__.py
utils/batch_processing.py
utils/caching.py
utils/connection_pool.py
utils/error_handler.py
utils/file_handling.py
utils/localization.py
utils/logger.py
utils/pagination.py
utils/rate_limiter.py
utils/security.py
telegram_advanced-0.2.0.dist-info/METADATA
telegram_advanced-0.2.0.dist-info/WHEEL
telegram_advanced-0.2.0.dist-info/top_level.txt
telegram_advanced-0.2.0.dist-info/RECORD
