Metadata-Version: 2.1
Name: telegram-advanced
Version: 0.2.0
Summary: An advanced Telegram bot library
Home-page: https://github.com/yourusername/telegram_advanced
Author: LCF
Author-email: your.email@example.com
Classifier: Programming Language :: Python :: 3
Classifier: License :: OSI Approved :: MIT License
Classifier: Operating System :: OS Independent
Requires-Dist: requests
